Metadata-Version: 2.1
Name: trimnami
Version: 0.1.4
Summary: Trim lots of metagenomics samples all at once.
Home-page: https://github.com/beardymcjohnface/Trimnami
Author: Michael Roach
Author-email: beardymcjohnface@gmail.com
Requires-Python: >=3.9
Requires-Dist: snaketool-utils >=0.0.5
Requires-Dist: snakemake <8,>=7.29
Requires-Dist: pulp <2.8
Requires-Dist: pyyaml >=6.0
Requires-Dist: Click >=8.1.3
Requires-Dist: metasnek >=0.0.8
